[
  {
    "vectorizer": "tfidf_default",
    "models": {
      "custom_kmeans": {
        "homogeneity": {
          "mean": 0.2935844123867544,
          "std": 0.008903077439174368,
          "min": 0.2805199181590429,
          "max": 0.30803145989676733
        },
        "completeness": {
          "mean": 0.36948384853507393,
          "std": 0.010357971020686165,
          "min": 0.3557365602892577,
          "max": 0.39020230727826877
        },
        "v_measure": {
          "mean": 0.3271137088649739,
          "std": 0.007967386097946259,
          "min": 0.31473333961382155,
          "max": 0.33670827079982857
        },
        "adjusted_rand": {
          "mean": 0.07328942185430551,
          "std": 0.009113795141381135,
          "min": 0.06260676372289906,
          "max": 0.08944837591732209
        },
        "silhouette": {
          "mean": 0.004775191471456061,
          "std": 0.002395502945170772,
          "min": 0.00043129307863449146,
          "max": 0.00690373384985004
        }
      },
      "sklearn_kmeans": {
        "homogeneity": {
          "mean": 0.29536890110725633,
          "std": 0.018333301881268086,
          "min": 0.2651901409733099,
          "max": 0.3128109151870644
        },
        "completeness": {
          "mean": 0.3697495129458127,
          "std": 0.020335811207144724,
          "min": 0.3354181930629236,
          "max": 0.3898305312236855
        },
        "v_measure": {
          "mean": 0.3283519097696186,
          "std": 0.018948165329027048,
          "min": 0.2961983471178521,
          "max": 0.34624864029163566
        },
        "adjusted_rand": {
          "mean": 0.07502738483737388,
          "std": 0.007663710986866663,
          "min": 0.06140116463249849,
          "max": 0.08716823692389185
        },
        "silhouette": {
          "mean": 0.0052595418771002505,
          "std": 0.0014370805004838714,
          "min": 0.0032509935499496533,
          "max": 0.00819802229833561
        }
      },
      "minibatch_kmeans": {
        "homogeneity": {
          "mean": 0.005370458345811181,
          "std": 0.00539444697268017,
          "min": 0.0010508800205982396,
          "max": 0.013650705613313305
        },
        "completeness": {
          "mean": 0.18606437928288455,
          "std": 0.11886117973360627,
          "min": 0.04527952760030421,
          "max": 0.2820543718202809
        },
        "v_measure": {
          "mean": 0.008931409368411308,
          "std": 0.008404969679582814,
          "min": 0.0020937540815316458,
          "max": 0.02129603336422711
        },
        "adjusted_rand": {
          "mean": 0.0021783288492058252,
          "std": 0.0028597995358717854,
          "min": -7.847194985998054e-06,
          "max": 0.006583353213929138
        },
        "silhouette": {
          "mean": -0.012659230501608752,
          "std": 0.03420537806728009,
          "min": -0.10932550213592122,
          "max": 0.006754183554980673
        }
      }
    },
    "significance": {
      "sklearn_kmeans": {
        "homogeneity": {
          "mean_difference": -0.0017844887205019032,
          "ci_low": -0.018504755688612377,
          "ci_high": 0.01730074503479596,
          "p_value": 0.8227376484756587
        },
        "completeness": {
          "mean_difference": -0.00026566441073872513,
          "ci_low": -0.016061730791437627,
          "ci_high": 0.015432140400124975,
          "p_value": 0.9684126258579295
        },
        "v_measure": {
          "mean_difference": -0.0012382009046446763,
          "ci_low": -0.017700683627201612,
          "ci_high": 0.015933639803502014,
          "p_value": 0.8666932842936422
        },
        "adjusted_rand": {
          "mean_difference": -0.0017379629830683516,
          "ci_low": -0.011922525531202682,
          "ci_high": 0.009455794369944174,
          "p_value": 0.7169679898063361
        },
        "silhouette": {
          "mean_difference": -0.00048435040564418896,
          "ci_low": -0.002154419213447469,
          "ci_high": 0.0012249427318492252,
          "p_value": 0.5133757903756218
        }
      },
      "minibatch_kmeans": {
        "homogeneity": {
          "mean_difference": 0.28821395404094324,
          "ci_low": 0.28282797393929776,
          "ci_high": 0.2936474432201789,
          "p_value": 4.847177837192361e-16
        },
        "completeness": {
          "mean_difference": 0.18341946925218938,
          "ci_low": 0.09969108891949455,
          "ci_high": 0.2747023424812588,
          "p_value": 0.0007651238404993609
        },
        "v_measure": {
          "mean_difference": 0.31818229949656257,
          "ci_low": 0.31086156540285814,
          "ci_high": 0.3257067137319424,
          "p_value": 4.5780632793024516e-15
        },
        "adjusted_rand": {
          "mean_difference": 0.0711110930050997,
          "ci_low": 0.06605110357706401,
          "ci_high": 0.07649374387140329,
          "p_value": 1.5795740729243e-10
        },
        "silhouette": {
          "mean_difference": 0.017434421973064808,
          "ci_low": 0.005037052931441516,
          "ci_high": 0.048161174354041394,
          "p_value": 0.12463261089189039
        }
      }
    }
  },
  {
    "vectorizer": "tfidf_bigram",
    "models": {
      "custom_kmeans": {
        "homogeneity": {
          "mean": 0.25959564395757695,
          "std": 0.012982875267863445,
          "min": 0.2409762211753779,
          "max": 0.2819416991365188
        },
        "completeness": {
          "mean": 0.36834032733207306,
          "std": 0.017803325823750084,
          "min": 0.32817423669258433,
          "max": 0.39316850141172077
        },
        "v_measure": {
          "mean": 0.3044819983460373,
          "std": 0.014294309561684896,
          "min": 0.28036391936103944,
          "max": 0.32839259500140994
        },
        "adjusted_rand": {
          "mean": 0.055494758555940084,
          "std": 0.007326846881370512,
          "min": 0.04749208279705971,
          "max": 0.06729521517096108
        },
        "silhouette": {
          "mean": 0.023101145245272688,
          "std": 0.005608278802857418,
          "min": 0.016294826659337944,
          "max": 0.03498548155131786
        }
      },
      "sklearn_kmeans": {
        "homogeneity": {
          "mean": 0.26756741391549754,
          "std": 0.018073874691389134,
          "min": 0.23610703370272093,
          "max": 0.2949605022075735
        },
        "completeness": {
          "mean": 0.3855699137059208,
          "std": 0.018764356142971783,
          "min": 0.35414387275448667,
          "max": 0.4165287870853599
        },
        "v_measure": {
          "mean": 0.3157725304822764,
          "std": 0.018013062301369415,
          "min": 0.28951844191977233,
          "max": 0.3453587905580562
        },
        "adjusted_rand": {
          "mean": 0.0556033374277234,
          "std": 0.005669030889632021,
          "min": 0.045774578857906735,
          "max": 0.06432052720129695
        },
        "silhouette": {
          "mean": 0.019180576727631685,
          "std": 0.007552067325405511,
          "min": 0.006558174492629865,
          "max": 0.027203266773903483
        }
      },
      "minibatch_kmeans": {
        "homogeneity": {
          "mean": 0.09952704345128668,
          "std": 0.0950542388759605,
          "min": 0.014781731907406817,
          "max": 0.24377476459971234
        },
        "completeness": {
          "mean": 0.20780719949701448,
          "std": 0.08542953351765678,
          "min": 0.09063618335707407,
          "max": 0.32660781302594366
        },
        "v_measure": {
          "mean": 0.12092374667067776,
          "std": 0.09710358982516173,
          "min": 0.027786655496569227,
          "max": 0.26188578427501025
        },
        "adjusted_rand": {
          "mean": 0.030298314834932914,
          "std": 0.03944146278422105,
          "min": 0.00010034551265724404,
          "max": 0.09489041100662857
        },
        "silhouette": {
          "mean": -0.09513793690488914,
          "std": 0.08553716885812929,
          "min": -0.18859887724154137,
          "max": 0.01960221356213968
        }
      }
    },
    "significance": {
      "sklearn_kmeans": {
        "homogeneity": {
          "mean_difference": -0.007971769957920613,
          "ci_low": -0.025654880091620556,
          "ci_high": 0.009436763663180225,
          "p_value": 0.29944209462079335
        },
        "completeness": {
          "mean_difference": -0.017229586373847788,
          "ci_low": -0.03727896695713662,
          "ci_high": 0.0005359418479311369,
          "p_value": 0.05972359163851932
        },
        "v_measure": {
          "mean_difference": -0.011290532136239017,
          "ci_low": -0.029054738325400946,
          "ci_high": 0.005264743401927483,
          "p_value": 0.15338484159058066
        },
        "adjusted_rand": {
          "mean_difference": -0.00010857887178330611,
          "ci_low": -0.007605182188865285,
          "ci_high": 0.00621546760846366,
          "p_value": 0.9724382047612716
        },
        "silhouette": {
          "mean_difference": 0.003920568517641002,
          "ci_low": -0.001219010447166661,
          "ci_high": 0.00920352270095261,
          "p_value": 0.11451781368220797
        }
      },
      "minibatch_kmeans": {
        "homogeneity": {
          "mean_difference": 0.16006860050629027,
          "ci_low": 0.08056749030594283,
          "ci_high": 0.22667233555721825,
          "p_value": 0.0006893673445836991
        },
        "completeness": {
          "mean_difference": 0.16053312783505852,
          "ci_low": 0.09221134224233654,
          "ci_high": 0.22622000874151216,
          "p_value": 0.00029123542031161937
        },
        "v_measure": {
          "mean_difference": 0.18355825167535958,
          "ci_low": 0.10493394037357637,
          "ci_high": 0.2518143720009317,
          "p_value": 0.00028681197175027166
        },
        "adjusted_rand": {
          "mean_difference": 0.025196443721007163,
          "ci_low": -0.007318939907255396,
          "ci_high": 0.05356921593729836,
          "p_value": 0.08708044527809021
        },
        "silhouette": {
          "mean_difference": 0.11823908215016184,
          "ci_low": 0.05017720667934365,
          "ci_high": 0.18630241958944588,
          "p_value": 0.0021940974531264026
        }
      }
    }
  },
  {
    "vectorizer": "count_binary",
    "models": {
      "custom_kmeans": {
        "homogeneity": {
          "mean": 0.026423706875171694,
          "std": 0.01589380750922029,
          "min": 0.013173797929049174,
          "max": 0.05371224953130166
        },
        "completeness": {
          "mean": 0.0920338060793197,
          "std": 0.03317941987845689,
          "min": 0.05284685589698094,
          "max": 0.16018861056544706
        },
        "v_measure": {
          "mean": 0.04053510214487777,
          "std": 0.022127030538431885,
          "min": 0.021090181948422864,
          "max": 0.08044933170322094
        },
        "adjusted_rand": {
          "mean": 0.004479729668154948,
          "std": 0.00249739271747771,
          "min": 0.002747761864358532,
          "max": 0.00917606530602672
        },
        "silhouette": {
          "mean": 0.13453699568354066,
          "std": 0.087584610472088,
          "min": 0.004628394198106712,
          "max": 0.26845328202036944
        }
      },
      "sklearn_kmeans": {
        "homogeneity": {
          "mean": 0.023442428941905714,
          "std": 0.014351054236512015,
          "min": 0.015064196220923072,
          "max": 0.05337213888242493
        },
        "completeness": {
          "mean": 0.07994094819271368,
          "std": 0.03190618292600605,
          "min": 0.0545429959896532,
          "max": 0.15182427594522335
        },
        "v_measure": {
          "mean": 0.03598311430679405,
          "std": 0.020100176160231187,
          "min": 0.023975540167568265,
          "max": 0.07897980428438012
        },
        "adjusted_rand": {
          "mean": 0.003983816877922542,
          "std": 0.002246523070432635,
          "min": 0.002652444021017885,
          "max": 0.0089399703185504
        },
        "silhouette": {
          "mean": 0.12525242159494493,
          "std": 0.10166483731645912,
          "min": -0.05157179799890901,
          "max": 0.26179400095692335
        }
      },
      "minibatch_kmeans": {
        "homogeneity": {
          "mean": 0.008530859823415263,
          "std": 0.01037155387118248,
          "min": 0.001312458806180014,
          "max": 0.03630065213958463
        },
        "completeness": {
          "mean": 0.09295502284209403,
          "std": 0.09902144356937875,
          "min": 0.019019303277971435,
          "max": 0.2768994021778919
        },
        "v_measure": {
          "mean": 0.01285416577677074,
          "std": 0.013195753853221429,
          "min": 0.0026123626910139557,
          "max": 0.047186329041823336
        },
        "adjusted_rand": {
          "mean": 0.00371034418233104,
          "std": 0.005566985612470841,
          "min": -8.367295723855602e-05,
          "max": 0.018539559012601955
        },
        "silhouette": {
          "mean": -0.1983370193644796,
          "std": 0.0907764444035163,
          "min": -0.30860190425815553,
          "max": -0.046942442976665076
        }
      }
    },
    "significance": {
      "sklearn_kmeans": {
        "homogeneity": {
          "mean_difference": 0.002981277933265978,
          "ci_low": -0.01668425145736151,
          "ci_high": 0.021742718323453057,
          "p_value": 0.7172259942898795
        },
        "completeness": {
          "mean_difference": 0.012092857886606025,
          "ci_low": -0.03345818255819931,
          "ci_high": 0.05507997929657924,
          "p_value": 0.5223882844098255
        },
        "v_measure": {
          "mean_difference": 0.0045519878380837105,
          "ci_low": -0.023606920030643398,
          "ci_high": 0.03077591609168068,
          "p_value": 0.6942314007840362
        },
        "adjusted_rand": {
          "mean_difference": 0.0004959127902324073,
          "ci_low": -0.0022738915120199266,
          "ci_high": 0.0034392823525341105,
          "p_value": 0.6956463898745705
        },
        "silhouette": {
          "mean_difference": 0.009284574088595737,
          "ci_low": -0.0598593146014007,
          "ci_high": 0.08953870510853178,
          "p_value": 0.7816605474710262
        }
      },
      "minibatch_kmeans": {
        "homogeneity": {
          "mean_difference": 0.01789284705175643,
          "ci_low": 0.0008423462833239343,
          "ci_high": 0.03232044773156347,
          "p_value": 0.025755203314344333
        },
        "completeness": {
          "mean_difference": -0.0009212167627743282,
          "ci_low": -0.07693711216552385,
          "ci_high": 0.06262501363387739,
          "p_value": 0.9761823443334946
        },
        "v_measure": {
          "mean_difference": 0.027680936368107024,
          "ci_low": 0.007028442850281929,
          "ci_high": 0.04910340599931043,
          "p_value": 0.013391957126520951
        },
        "adjusted_rand": {
          "mean_difference": 0.000769385485823908,
          "ci_low": -0.005466945315082984,
          "ci_high": 0.0048396279227082015,
          "p_value": 0.7227221897677073
        },
        "silhouette": {
          "mean_difference": 0.3328740150480203,
          "ci_low": 0.24561374630063354,
          "ci_high": 0.43406817207134685,
          "p_value": 1.4010890814232256e-05
        }
      }
    }
  }
]